CHANGES.txt
LICENSE.txt
MANIFEST.in
README.txt
setup.py
js/__init__.py
js.jquery_fullcalendar.egg-info/PKG-INFO
js.jquery_fullcalendar.egg-info/SOURCES.txt
js.jquery_fullcalendar.egg-info/dependency_links.txt
js.jquery_fullcalendar.egg-info/entry_points.txt
js.jquery_fullcalendar.egg-info/namespace_packages.txt
js.jquery_fullcalendar.egg-info/not-zip-safe
js.jquery_fullcalendar.egg-info/requires.txt
js.jquery_fullcalendar.egg-info/top_level.txt
js/jquery_fullcalendar/__init__.py
js/jquery_fullcalendar/test_jquery_fullcalendar.txt
js/jquery_fullcalendar/resources/fullcalendar.css
js/jquery_fullcalendar/resources/fullcalendar.js
js/jquery_fullcalendar/resources/fullcalendar.min.js
js/jquery_fullcalendar/resources/fullcalendar.print.css