Metadata-Version: 1.0
Name: js.jquery-fullcalendar
Version: 1.5.2
Summary: Fanstatic packaging of jQuery FullCalendar
Home-page: UNKNOWN
Author: Fanstatic Developers
Author-email: fanstatic@googlegroups.com
License: BSD
Platform: UNKNOWN
